c2pa_text/__init__.py
c2pa_text/validator.py
c2pa_text-1.0.3.dist-info/WHEEL
c2pa_text-1.0.3.dist-info/METADATA
c2pa_text-1.0.3.dist-info/RECORD
