Metadata-Version: 2.4
Name: c2pa-text
Version: 1.0.3
Summary: Reference implementation for embedding C2PA manifests in text using Unicode variation selectors
Author-email: Encypher Corporation <contact@encypherai.com>
Requires-Python: >=3.8
Classifier: Development Status :: 5 - Production/Stable
Classifier: Intended Audience :: Developers
Classifier: License :: OSI Approved :: MIT License
Classifier: Programming Language :: Python :: 3
Classifier: Topic :: Security :: Cryptography
Classifier: Topic :: Text Processing
Requires-Dist: pytest>=7.0 ; extra == "dev"
Requires-Dist: pytest-cov>=4.0 ; extra == "dev"
Requires-Dist: ruff>=0.1.0 ; extra == "dev"
Provides-Extra: dev
